{
  "description": "Доставка товару здійснюється за рахунок Постачальника, його транспортом чи транспортом перевізника за рахунок Постачальника.",
  "date": "2026-06-09T00:00:27.264871+03:00",
  "dateModified": "2026-06-09T00:02:51.714009+03:00",
  "dateCreated": "2026-05-29T16:40:53.624125+03:00",
  "tenderID": "UA-2026-05-29-009496-a",
  "documents": [
    {
      "confidentiality": "public",
      "documentType": "biddingDocuments",
      "id": "73594949a9b74127b5b958e2715fef19",
      "datePublished": "2026-05-29T16:40:55.581949+03:00",
      "hash": "md5:2380c1e56f9a50af125bb84652594dc7",
      "title": "1. Оголошення.doc",
      "format": "application/msword",
      "url": "https://public-docs.prozorro.gov.ua/get/77546b3dee8f49a0ae735317340efe77?Signature=NjGcVgBdat40ZmAt61xse%2BnDf5e2qFCXZ8XmYjxeHwEl4NsAPyVgwRtp%2BgZwkrwACVCkvAnCDa%2Fpnhatu5kaCg%3D%3D&KeyID=52462340",
      "documentOf": "tender",
      "dateModified": "2026-05-29T16:40:55.581949+03:00",
      "author": "tender_owner",
      "language": "uk"
    },
    {
      "confidentiality": "public",
      "documentType": "biddingDocuments",
      "id": "cc288da5333f4f89a05b620cacdf4181",
      "datePublished": "2026-05-29T16:40:55.581949+03:00",
      "hash": "md5:bfca041bff8f93f12a49e01c9fc3d391",
      "title": "Додаток 1 Документи що подаються Учасниками.doc",
      "format": "application/msword",
      "url": "https://public-docs.prozorro.gov.ua/get/f4690c12a98447d2a8c16704fac01f88?Signature=YbIj6Zf4qB%2BGnCJEjzzhrGyt5S%2FuHn5NcRmqZrot7Iv5qHIPW5jGzPbXPs%2BwGLwFWngMXmJG853P1G05GRbgCw%3D%3D&KeyID=52462340",
      "documentOf": "tender",
      "dateModified": "2026-05-29T16:40:55.581949+03:00",
      "author": "tender_owner",
      "language": "uk"
    },
    {
      "confidentiality": "public",
      "documentType": "technicalSpecifications",
      "id": "f1425b25d06c428dac75c96060cf6895",
      "datePublished": "2026-05-29T16:40:55.581949+03:00",
      "hash": "md5:a33868d272418262e37dc525fedb7848",
      "title": "Додаток 2 Технічне завдання.docx",
      "format": "application/vnd.openxmlformats-officedocument.wordprocessingml.document",
      "url": "https://public-docs.prozorro.gov.ua/get/bf0897c0b91c42caa0924e0d2c563ed1?Signature=glGm6U6A5MlV0N5m4UoILX8xly4ZRrCzAFDSYIjzLvrVuGREixvZ8MoNss1MK5cdFGAJ%2BPyV4hDxjDa1tm1IDA%3D%3D&KeyID=52462340",
      "documentOf": "tender",
      "dateModified": "2026-05-29T16:40:55.581949+03:00",
      "author": "tender_owner",
      "language": "uk"
    },
    {
      "confidentiality": "public",
      "documentType": "biddingDocuments",
      "id": "ec0d815b483840bca5c2dbe0d13841ef",
      "datePublished": "2026-05-29T16:40:55.581949+03:00",
      "hash": "md5:d2482de967ad3ac738aa41c2c1a1d1b3",
      "title": "Додаток 3 Пропозиція.doc",
      "format": "application/msword",
      "url": "https://public-docs.prozorro.gov.ua/get/dc360fe3b7784d5f9a64a3bff65332a4?Signature=J4zz61bSMCFtfCLcbRXzofb3DtSj9K7GU3RFouQMCSl8x00gaQZPCu30jsvAk1TKWJbMAqR8eJlHXwInNc8CCw%3D%3D&KeyID=52462340",
      "documentOf": "tender",
      "dateModified": "2026-05-29T16:40:55.581949+03:00",
      "author": "tender_owner",
      "language": "uk"
    },
    {
      "confidentiality": "public",
      "documentType": "biddingDocuments",
      "id": "0e54d38fe94648e4aad45fdcc646d66e",
      "datePublished": "2026-05-29T16:40:55.581949+03:00",
      "hash": "md5:8991fd0ad583cd4c4edef70cf0dcd62b",
      "title": "Додаток 4 Довідка-підтвердження.doc",
      "format": "application/msword",
      "url": "https://public-docs.prozorro.gov.ua/get/b36e5a9b37bd412e94043341d4c767c7?Signature=mOj50ahYPcoFZL0dAaG%2FkucxfShxAjUWlSGPEgp8UEYV3EQAIyQxIo8wGPhm1dRdZF%2FsCImrGICgoalZ%2Fm33Aw%3D%3D&KeyID=52462340",
      "documentOf": "tender",
      "dateModified": "2026-05-29T16:40:55.581949+03:00",
      "author": "tender_owner",
      "language": "uk"
    },
    {
      "confidentiality": "public",
      "documentType": "contractProforma",
      "id": "5f4185b1826e43558589dcb52c71f4a5",
      "datePublished": "2026-05-29T16:40:55.581949+03:00",
      "hash": "md5:3d40de636a9132b1e7d299baf4aafd74",
      "title": "Проєкт Договору .doc",
      "format": "application/msword",
      "url": "https://public-docs.prozorro.gov.ua/get/8ee097a1d2cd4e1fb0b391bbb6ec45c7?Signature=lImIqMOP25ISh%2Bh7S67iAHgidyLilSWZm1yzBO8GKtMMK1QVpY6SnT4QAs%2Ff1n%2BkdeHb5bG2j9uYSZK803unBA%3D%3D&KeyID=52462340",
      "documentOf": "tender",
      "dateModified": "2026-05-29T16:40:55.581949+03:00",
      "author": "tender_owner",
      "language": "uk"
    },
    {
      "confidentiality": "public",
      "documentType": "notice",
      "id": "438864600533469981ee9de5d59c911e",
      "datePublished": "2026-05-29T16:41:00.918140+03:00",
      "hash": "md5:9dbd14f2d21eff37ac6f0f8c5f2da900",
      "title": "sign.p7s",
      "format": "application/pkcs7-signature",
      "url": "https://public-docs.prozorro.gov.ua/get/23ad7f4a0fa54f5ba8720bcdad477b44?Signature=vaZemzMLuNYNkyIp%2Bq1Rka3rrAJz4alG4NXSd5bzheguek16P7%2BmS%2BPsBsmDIuNcGftY3IPI5PlSHSL%2F0kYKDA%3D%3D&KeyID=52462340",
      "documentOf": "tender",
      "dateModified": "2026-05-29T16:41:00.918140+03:00",
      "author": "tender_owner",
      "language": "uk"
    }
  ],
  "status": "active.auction",
  "owner": "it.ua",
  "title": "автомобільні шини",
  "mainProcurementCategory": "goods",
  "procurementMethod": "open",
  "contractChangeRationaleTypes": {
    "durationExtension": {
      "description_en": "Extension of the period of the procurement contract duration and the term of obligations fulfilment regarding the transfer of goods, implementation of works and provision of services in case of documented objective circumstances that led to such extension, including circumstances of force majeure, delays in funding of procuring entitys expenditures, provided that such changes will not increase the sum of money specified in the procurement contract",
      "title_en": "Clause 4, Part 5, Article 41 of the Law of Ukraine dated 25.12.2015 No. 922-VIII \"On Public Procurement\"",
      "description_uk": "Продовження строку дії договору про закупівлю та строку виконання зобов’язань щодо передачі товару, виконання робіт, надання послуг у разі виникнення документально підтверджених об’єктивних обставин, що спричинили таке продовження, у тому числі обставин непереборної сили, затримки фінансування витрат замовника, за умови що такі зміни не призведуть до збільшення суми, визначеної в договорі про закупівлю",
      "title_uk": "Пункт 4 частини 5 статті 41 Закону України від 25.12.2015 № 922-VIII \"Про публічні закупівлі\""
    },
    "fiscalYearExtension": {
      "description_en": "Еffect of the procurement contract may be extended for a period sufficient for conduction of the procurement procedure/simplified procurement at the beginning of the next year in volume that does not exceed 20% of the sum specified in the initial procurement contract concluded in the previous year, if expenditures for achieving this goal are approved in the prescribed manner",
      "title_en": "Part 6 of Article 41 of the Law of Ukraine dated 25.12.2015 No. 922-VIII \"On Public Procurement\"",
      "description_uk": "Дія договору про закупівлю може бути продовжена на строк, достатній для проведення процедури закупівлі/спрощеної закупівлі на початку наступного року в обсязі, що не перевищує 20 відсотків суми, визначеної в початковому договорі про закупівлю, укладеному в попередньому році, якщо видатки на досягнення цієї цілі затверджено в установленому порядку",
      "title_uk": "Частина 6 статті 41 Закону України від 25.12.2015 № 922-VIII \"Про публічні закупівлі\""
    },
    "priceClarification": {
      "description_en": "Drawing up a contract price, specified in accordance with the approved project documentation for the purchase contract, specified in paragraph three of part one of this article",
      "title_en": "Clause 2, Part 7, Article 41 of the Law of Ukraine dated 25.12.2015 No. 922-VIII \"On Public Procurement\"",
      "description_uk": "Складання договірної ціни, уточненої відповідно до затвердженої проектної документації до договору про закупівлю, зазначеного в абзаці третьому частини першої цієї статті",
      "title_uk": "Пункт 2 частини 7 статті 41 Закону України від 25.12.2015 № 922-VIII \"Про публічні закупівлі\""
    },
    "itemPriceVariation": {
      "description_en": "An increase in the price per unit of goods by up to 10 percent in proportion to the increase in the market price of such goods in the event of fluctuations in the market price of such goods, provided that such a change does not lead to an increase in the amount specified in the procurement contract; - no more than once every 90 days from the date of signing the procurement contract/making changes to such a contract regarding an increase in the price per unit of goods. The restriction on the timing of changes in the price per unit of goods does not apply in cases of changes in the terms of the contract for the procurement of gasoline and diesel fuel, natural gas, and electricity",
      "title_en": "Clause 2, Part 5, Article 41 of the Law of Ukraine dated 25.12.2015 No. 922-VIII \"On Public Procurement\"",
      "description_uk": "Збільшення ціни за одиницю товару до 10 відсотків пропорційно збільшенню ціни такого товару на ринку у разі коливання ціни такого товару на ринку за умови, що така зміна не призведе до збільшення суми, визначеної в договорі про закупівлю, - не частіше ніж один раз на 90 днів з моменту підписання договору про закупівлю/внесення змін до такого договору щодо збільшення ціни за одиницю товару. Обмеження щодо строків зміни ціни за одиницю товару не застосовується у випадках зміни умов договору про закупівлю бензину та дизельного пального, природного газу та електричної енергії",
      "title_uk": "Пункт 2 частини 5 статті 41 Закону України від 25.12.2015 № 922-VIII \"Про публічні закупівлі\""
    },
    "priceReduction": {
      "description_en": "Аpproval of price changes in the procurement contract in the direction of reduction (without changing the quantity (volume) and quality of goods, works and services), including in case of fluctuations in the price of goods on the market",
      "title_en": "Clause 5, Part 5, Article 41 of the Law of Ukraine dated 25.12.2015 No. 922-VIII \"On Public Procurement\"",
      "description_uk": "Погодження зміни ціни в договорі про закупівлю в бік зменшення (без зміни кількості (обсягу) та якості товарів, робіт і послуг), у тому числі у разі коливання ціни товару на ринку",
      "title_uk": "Пункт 5 частини 5 статті 41 Закону України від 25.12.2015 № 922-VIII \"Про публічні закупівлі\""
    },
    "qualityImprovement": {
      "description_en": "Іmprovement of the item's quality, provided that such improvement will not increase the sum of money specified in the procurement contract",
      "title_en": "Clause 3, Part 5, Article 41 of the Law of Ukraine dated 25.12.2015 No. 922-VIII \"On Public Procurement\"",
      "description_uk": "Покращення якості предмета закупівлі, за умови що таке покращення не призведе до збільшення суми, визначеної в договорі про закупівлю",
      "title_uk": "Пункт 3 частини 5 статті 41 Закону України від 25.12.2015 № 922-VIII \"Про публічні закупівлі\""
    },
    "taxRate": {
      "description_en": "Changes in the price in the purchase contract due to changes in tax and duty rates and/or changes in the conditions for granting tax benefits - in proportion to the change in such rates and/or tax benefits",
      "title_en": "Clause 6, Part 5, Article 41 of the Law of Ukraine dated 25.12.2015 No. 922-VIII \"On Public Procurement\"",
      "description_uk": "Зміни ціни в договорі про закупівлю у зв’язку зі зміною ставок податків і зборів та/або зміною умов щодо надання пільг з оподаткування - пропорційно до зміни таких ставок та/або пільг з оподаткування",
      "title_uk": "Пункт 6 частини 5 статті 41 Закону України від 25.12.2015 № 922-VIII \"Про публічні закупівлі\""
    },
    "thirdParty": {
      "description_en": "Changes in the consumer price index established in accordance with the legislation by state statistics bodies, changes in foreign currency exchange rates, changes in stock market quotes or Platts, ARGUS indicators of regulated prices (tariffs) and standards applied in the procurement contract, if the procurement contract establishes the procedure for changing the price",
      "title_en": "Clause 7, Part 5, Article 41 of the Law of Ukraine dated 25.12.2015 No. 922-VIII \"On Public Procurement\"",
      "description_uk": "Зміни встановленого згідно із законодавством органами державної статистики індексу споживчих цін, зміни курсу іноземної валюти, зміни біржових котирувань або показників Platts, ARGUS регульованих цін (тарифів) і нормативів, що застосовуються в договорі про закупівлю, у разі встановлення в договорі про закупівлю порядку зміни ціни",
      "title_uk": "Пункт 7 частини 5 статті 41 Закону України від 25.12.2015 № 922-VIII \"Про публічні закупівлі\""
    },
    "volumeCuts": {
      "description_en": "Reduction of the procurement's volume, particularly taking into account the actual expenditures of the procuring entity",
      "title_en": "Clause 1, Part 5, Article 41 of the Law of Ukraine dated 25.12.2015 No. 922-VIII \"On Public Procurement\"",
      "description_uk": "Зменшення обсягів закупівлі, зокрема з урахуванням фактичного обсягу видатків замовника",
      "title_uk": "Пункт 1 частини 5 статті 41 Закону України від 25.12.2015 № 922-VIII \"Про публічні закупівлі\""
    }
  },
  "milestones": [
    {
      "id": "cacaee9d25c7493da9fbfbd4dbd7ecfe",
      "title": "deliveryOfGoods",
      "description": "Попередня оплата (аванс) не передбачені",
      "type": "financing",
      "code": "postpayment",
      "percentage": 100.0,
      "duration": {
        "days": 5,
        "type": "working"
      },
      "sequenceNumber": 1,
      "relatedLot": "af20b3faf7194444ae40ad238a6d81c3"
    },
    {
      "id": "dc79afcc7b7440dd9f4875e1e2889362",
      "title": "signingTheContract",
      "description": "Термін постачання: партіями, за заявкою Замовника (що погоджуються сторонами), але не пізніше 28 червня 2026 року. розглянемо також одноразову поставку",
      "type": "delivery",
      "code": "recurring",
      "percentage": 100.0,
      "duration": {
        "days": 17,
        "type": "calendar"
      },
      "sequenceNumber": 2,
      "relatedLot": "af20b3faf7194444ae40ad238a6d81c3"
    }
  ],
  "submissionMethod": "electronicAuction",
  "awardCriteria": "lowestCost",
  "procuringEntity": {
    "name": "ВІЙСЬКОВА ЧАСТИНА 3002 НАЦІОНАЛЬНОЇ ГВАРДІЇ УКРАЇНИ",
    "identifier": {
      "scheme": "UA-EDR",
      "id": "08682683",
      "legalName": "ВІЙСЬКОВА ЧАСТИНА 3002 НАЦІОНАЛЬНОЇ ГВАРДІЇ УКРАЇНИ"
    },
    "address": {
      "streetAddress": "м. Львів",
      "locality": "Львів",
      "region": "Львівська область",
      "postalCode": "79060",
      "countryName": "Україна"
    },
    "contactPoint": {
      "name": "Роман Савчук",
      "email": "r.savchuk@ngu.gov.ua",
      "telephone": "380322634214"
    },
    "kind": "defense"
  },
  "value": {
    "currency": "UAH",
    "valueAddedTaxIncluded": false,
    "amount": 160590.0
  },
  "tenderPeriod": {
    "startDate": "2026-06-04T15:00:00+03:00",
    "endDate": "2026-06-09T00:00:00+03:00"
  },
  "lots": [
    {
      "title": "автомобільні шини (спецпризначення)",
      "description": "Закупівля здійснюється відповідно до ПКМУ 1275 від 11.11.2022 Деякі питання здійснення оборонних закупівель на період дії правового режиму воєнного стану",
      "status": "active",
      "id": "af20b3faf7194444ae40ad238a6d81c3",
      "date": "2026-05-29T16:40:53.624125+03:00",
      "value": {
        "currency": "UAH",
        "valueAddedTaxIncluded": false,
        "amount": 160590.0
      },
      "minimalStep": {
        "currency": "UAH",
        "valueAddedTaxIncluded": false,
        "amount": 802.95
      },
      "auctionPeriod": {
        "startDate": "2026-06-09T13:48:58.156000+03:00",
        "shouldStartAfter": "2026-06-09T00:00:00+03:00"
      },
      "auctionUrl": "https://auctions.prozorro.gov.ua/tenders/832d3e13149541129ddfd9ffec1c6e80_af20b3faf7194444ae40ad238a6d81c3"
    }
  ],
  "procurementMethodType": "belowThreshold",
  "enquiryPeriod": {
    "startDate": "2026-05-29T16:40:53.624125+03:00",
    "clarificationsUntil": "2026-06-06T00:00:00+03:00",
    "endDate": "2026-06-04T13:00:00+03:00"
  },
  "items": [
    {
      "id": "fed83b0ea55641b080fec8f520ae4be6",
      "description": "Шини Haida HD 725 205/65 R16C 107/105T (спецпризначення) (або еквівалент)",
      "unit": {
        "name": "штука",
        "code": "H87"
      },
      "quantity": 4.0,
      "classification": {
        "description": "Шини для транспортних засобів великої та малої тоннажності",
        "scheme": "ДК021",
        "id": "34350000-5"
      },
      "deliveryDate": {
        "endDate": "2026-06-28T00:00:00+03:00"
      },
      "deliveryAddress": {
        "streetAddress": "м. Львів",
        "locality": "Львів",
        "region": "Львівська область",
        "postalCode": "79060",
        "countryName": "Україна"
      },
      "relatedLot": "af20b3faf7194444ae40ad238a6d81c3"
    },
    {
      "id": "7ec6b61b304b4cd090362deb53696183",
      "description": "Шини Rauffan Vanzar R6E 215/60 R17C (спецпризначення)109/107T (або еквівалент)",
      "unit": {
        "name": "штука",
        "code": "H87"
      },
      "quantity": 4.0,
      "classification": {
        "description": "Шини для транспортних засобів великої та малої тоннажності",
        "scheme": "ДК021",
        "id": "34350000-5"
      },
      "deliveryDate": {
        "endDate": "2026-06-28T00:00:00+03:00"
      },
      "deliveryAddress": {
        "streetAddress": "м. Львів",
        "locality": "Львів",
        "region": "Львівська область",
        "postalCode": "79060",
        "countryName": "Україна"
      },
      "relatedLot": "af20b3faf7194444ae40ad238a6d81c3"
    },
    {
      "id": "fb436efdfe4c4e468d2b5bc78d0ae999",
      "description": "Шини Comforser CF350 235/65 R16C (спецпризначення)115/113R (або еквівалент)",
      "unit": {
        "name": "штука",
        "code": "H87"
      },
      "quantity": 4.0,
      "classification": {
        "description": "Шини для транспортних засобів великої та малої тоннажності",
        "scheme": "ДК021",
        "id": "34350000-5"
      },
      "deliveryDate": {
        "endDate": "2026-06-28T00:00:00+03:00"
      },
      "deliveryAddress": {
        "streetAddress": "м. Львів",
        "locality": "Львів",
        "region": "Львівська область",
        "postalCode": "79060",
        "countryName": "Україна"
      },
      "relatedLot": "af20b3faf7194444ae40ad238a6d81c3"
    },
    {
      "id": "21120c78f42c439fac912c02554c215b",
      "description": "Шини Firemax FM916 225/70 R15C 112/110R (спецпризначення) (або еквівалент)",
      "unit": {
        "name": "штука",
        "code": "H87"
      },
      "quantity": 8.0,
      "classification": {
        "description": "Шини для транспортних засобів великої та малої тоннажності",
        "scheme": "ДК021",
        "id": "34350000-5"
      },
      "deliveryDate": {
        "endDate": "2026-06-28T00:00:00+03:00"
      },
      "deliveryAddress": {
        "streetAddress": "м. Львів",
        "locality": "Львів",
        "region": "Львівська область",
        "postalCode": "79060",
        "countryName": "Україна"
      },
      "relatedLot": "af20b3faf7194444ae40ad238a6d81c3"
    },
    {
      "id": "a0cdb9ea249b4fb79887e003e36f08d4",
      "description": "Шини Rauffan Vanzar R6E 215/65 R16C (спецпризначення)109/107T (або еквівалент)",
      "unit": {
        "name": "штука",
        "code": "H87"
      },
      "quantity": 12.0,
      "classification": {
        "description": "Шини для транспортних засобів великої та малої тоннажності",
        "scheme": "ДК021",
        "id": "34350000-5"
      },
      "deliveryDate": {
        "endDate": "2026-06-28T00:00:00+03:00"
      },
      "deliveryAddress": {
        "streetAddress": "м. Львів",
        "locality": "Львів",
        "region": "Львівська область",
        "postalCode": "79060",
        "countryName": "Україна"
      },
      "relatedLot": "af20b3faf7194444ae40ad238a6d81c3"
    },
    {
      "id": "3d3f0ee93d974e9daa2c6230c685ceab",
      "description": "Шини Rauffan Vanzar R6E 205/65 R16C (спецпризначення)107/105T (або еквівалент)",
      "unit": {
        "name": "штука",
        "code": "H87"
      },
      "quantity": 4.0,
      "classification": {
        "description": "Шини для транспортних засобів великої та малої тоннажності",
        "scheme": "ДК021",
        "id": "34350000-5"
      },
      "deliveryDate": {
        "endDate": "2026-06-28T00:00:00+03:00"
      },
      "deliveryAddress": {
        "streetAddress": "м. Львів",
        "locality": "Львів",
        "region": "Львівська область",
        "postalCode": "79060",
        "countryName": "Україна"
      },
      "relatedLot": "af20b3faf7194444ae40ad238a6d81c3"
    },
    {
      "id": "174acbfe1840457693766158473dc6cc",
      "description": "Шини Rauffan Vanzar R6E 195/75 R16C (спецпризначення)107/105R (або еквівалент)",
      "unit": {
        "name": "штука",
        "code": "H87"
      },
      "quantity": 18.0,
      "classification": {
        "description": "Шини для транспортних засобів великої та малої тоннажності",
        "scheme": "ДК021",
        "id": "34350000-5"
      },
      "deliveryDate": {
        "endDate": "2026-06-28T00:00:00+03:00"
      },
      "deliveryAddress": {
        "streetAddress": "м. Львів",
        "locality": "Львів",
        "region": "Львівська область",
        "postalCode": "79060",
        "countryName": "Україна"
      },
      "relatedLot": "af20b3faf7194444ae40ad238a6d81c3"
    },
    {
      "id": "3c9c8f518e144bf1bf3f179c0aa0ca88",
      "description": "Шини Arivo Premio Eco 6 195/65 R15 91V (спецпризначення) (або еквівалент)",
      "unit": {
        "name": "штука",
        "code": "H87"
      },
      "quantity": 8.0,
      "classification": {
        "description": "Шини для транспортних засобів великої та малої тоннажності",
        "scheme": "ДК021",
        "id": "34350000-5"
      },
      "deliveryDate": {
        "endDate": "2026-06-28T00:00:00+03:00"
      },
      "deliveryAddress": {
        "streetAddress": "м. Львів",
        "locality": "Львів",
        "region": "Львівська область",
        "postalCode": "79060",
        "countryName": "Україна"
      },
      "relatedLot": "af20b3faf7194444ae40ad238a6d81c3"
    }
  ],
  "noticePublicationDate": "2026-05-29T16:41:02.478789+03:00",
  "next_check": "2026-06-09T13:48:58.156000+03:00",
  "id": "832d3e13149541129ddfd9ffec1c6e80"
}